ss/__init__.py
ss/control/__init__.py
ss/control/_control.py
ss/control/cost/__init__.py
ss/control/cost/_cost.py
ss/control/cost/_cost_quadratic.py
ss/control/cost/figure/__init__.py
ss/control/cost/figure/_figure.py
ss/control/mppi/README.md
ss/control/mppi/__init__.py
ss/control/mppi/_mppi.py
ss/control/optimal/__init__.py
ss/control/optimal/lqg.py
ss/control/optimal/lqr.py
ss/estimation/__init__.py
ss/estimation/_estimation.py
ss/estimation/dual_filtering/__init__.py
ss/estimation/dual_filtering/hmm/__init__.py
ss/estimation/dual_filtering/hmm/_hmm.py
ss/estimation/dual_filtering/hmm/learning/__init__.py
ss/estimation/dual_filtering/hmm/learning/module/__init__.py
ss/estimation/dual_filtering/hmm/learning/module/_module.py
ss/estimation/dual_filtering/hmm/learning/module/config/__init__.py
ss/estimation/dual_filtering/hmm/learning/module/config/_config.py
ss/estimation/dual_filtering/hmm/learning/module/emission/__init__.py
ss/estimation/dual_filtering/hmm/learning/module/emission/_emission.py
ss/estimation/dual_filtering/hmm/learning/module/emission/config/__init__.py
ss/estimation/dual_filtering/hmm/learning/module/emission/config/_config.py
ss/estimation/dual_filtering/hmm/learning/module/estimation/__init__.py
ss/estimation/dual_filtering/hmm/learning/module/estimation/_estimation.py
ss/estimation/dual_filtering/hmm/learning/module/estimation/config/__init__.py
ss/estimation/dual_filtering/hmm/learning/module/estimation/config/_config.py
ss/estimation/dual_filtering/hmm/learning/module/filter/__init__.py
ss/estimation/dual_filtering/hmm/learning/module/filter/_filter.py
ss/estimation/dual_filtering/hmm/learning/module/filter/config/__init__.py
ss/estimation/dual_filtering/hmm/learning/module/filter/config/_config.py
ss/estimation/dual_filtering/hmm/learning/module/transition/__init__.py
ss/estimation/dual_filtering/hmm/learning/module/transition/_transition.py
ss/estimation/dual_filtering/hmm/learning/module/transition/block/__init__.py
signal_system-0.0.2.dist-info/METADATA
signal_system-0.0.2.dist-info/WHEEL
signal_system-0.0.2.dist-info/licenses/LICENSE
signal_system-0.0.2.dist-info/RECORD
