Metadata-Version: 2.4
Name: Signal-System
Version: 0.0.2
Summary: A package for signal and system simulation, design, analysis, and learning.
Author-email: Heng-Sheng Chang <hanson.hschang+signal.system@gmail.com>
License-Expression: MIT
License-File: LICENSE
Keywords: Learning,Signal,System
Classifier: Development Status :: 4 - Beta
Classifier: Intended Audience :: Education
Classifier: Intended Audience :: Science/Research
Classifier: License :: OSI Approved :: MIT License
Classifier: Natural Language :: English
Classifier: Operating System :: OS Independent
Classifier: Programming Language :: Python :: 3
Classifier: Programming Language :: Python :: 3.13
Requires-Python: >=3.13
Requires-Dist: click>=8.1.7
Requires-Dist: h5py>=3.0.0
Requires-Dist: matplotlib>=3.7.2
Requires-Dist: numba>=0.60.0
Requires-Dist: numpy>=1.26.0
Requires-Dist: psutil>=6.1.1
Requires-Dist: scipy>=1.11.0
Requires-Dist: torch>=2.6.0
Requires-Dist: tqdm>=4.60.0
Provides-Extra: dev
Requires-Dist: black>=24.4.2; extra == 'dev'
Requires-Dist: codecov>=2.1.13; extra == 'dev'
Requires-Dist: isort[colors]>=5.13.2; extra == 'dev'
Requires-Dist: mypy-extensions>=1.0.0; extra == 'dev'
Requires-Dist: mypy>=1.10.0; extra == 'dev'
Requires-Dist: pip-tools>=7.4.0; extra == 'dev'
Requires-Dist: pre-commit>=3.7.1; extra == 'dev'
Requires-Dist: pytest-cov>=5.0.0; extra == 'dev'
Requires-Dist: pytest-dependency>=0.6.0; extra == 'dev'
Requires-Dist: pytest-mock>=3.14.0; extra == 'dev'
Requires-Dist: pytest>=8.2.1; extra == 'dev'
Requires-Dist: pyupgrade>=3.15.2; extra == 'dev'
